pmc_id_converter/__init__.py
pmc_id_converter/bin.py
pmc_id_converter/core.py
pmc_id_converter/version.json
pmc_id_converter-1.0.0.dist-info/METADATA
pmc_id_converter-1.0.0.dist-info/WHEEL
pmc_id_converter-1.0.0.dist-info/entry_points.txt
pmc_id_converter-1.0.0.dist-info/top_level.txt
pmc_id_converter-1.0.0.dist-info/RECORD
